rtl/layer1_axis_stream_ingress.v
// =============================================================
// layer1_axis_stream_ingress.v
//
// Layer 1 (AXI4-Stream Interface) per the SARCathon reference
// architecture, as its OWN standalone, independently-verifiable
// block — split out from the fused implementation kept at
// legacy_fused_layer1_3_axis_to_flit.v.
//
// This is a standard, fully-registered AXI4-Stream register slice
// ("skid buffer" without the skid path — a single buffered stage):
//   - Breaks any combinational path between the upstream driver
//     and whatever consumes m_t* (here, Layer 3's FLIT packetizer),
//     which is the actual "ingress" job Layer 1 is named for in the
//     spec's function table: buffering/presenting transaction data
//     at the system boundary.
//   - s_tready = m_tready | !m_tvalid: the slave side can always
//     accept a new beat unless the internal register is both full
//     AND the consumer isn't draining it this cycle. This gives
//     full back-to-back throughput (a new beat can be accepted
//     every cycle when the consumer keeps up) at the cost of
//     exactly 1 cycle of added latency per beat — the standard,
//     well-understood trade-off for this pattern.
//   - TKEEP/TLAST are carried through unchanged; this layer does
//     not interpret packet boundaries, only forwards them (that's
//     Layer 3's job).
// =============================================================

module layer1_axis_stream_ingress #(
    parameter TDATA_WIDTH = 512
)(
    input                              clk,
    input                              rst_n,

    // ---------------- AXI4-Stream Slave (system ingress) ----------------
    input      [TDATA_WIDTH-1:0]       s_tdata,
    input      [(TDATA_WIDTH/8)-1:0]   s_tkeep,
    input                              s_tvalid,
    output                             s_tready,
    input                              s_tlast,

    // ---------------- AXI4-Stream Master (to Layer 3) ----------------
    output reg [TDATA_WIDTH-1:0]       m_tdata,
    output reg [(TDATA_WIDTH/8)-1:0]   m_tkeep,
    output reg                         m_tvalid,
    input                              m_tready,
    output reg                         m_tlast
);

    assign s_tready = m_tready || !m_tvalid;

    always @(posedge clk or negedge rst_n) begin
        if (!rst_n) begin
            m_tvalid <= 1'b0;
            m_tdata  <= {TDATA_WIDTH{1'b0}};
            m_tkeep  <= {(TDATA_WIDTH/8){1'b0}};
            m_tlast  <= 1'b0;
        end else begin
            if (s_tready) begin
                m_tvalid <= s_tvalid;
                if (s_tvalid) begin
                    m_tdata <= s_tdata;
                    m_tkeep <= s_tkeep;
                    m_tlast <= s_tlast;
                end
            end
            // if !s_tready: buffer is full and consumer isn't draining
            // this cycle -> hold everything (no assignment => retains).
        end
    end

endmodule

tb/tb_layer1_axis_stream_ingress.v
`timescale 1ns/1ps

module tb_layer1_axis_stream_ingress;

    localparam TDATA_WIDTH = 512;
    localparam CLK_PERIOD  = 10;

    reg clk, rst_n;
    reg  [TDATA_WIDTH-1:0]     s_tdata;
    reg  [(TDATA_WIDTH/8)-1:0] s_tkeep;
    reg                        s_tvalid;
    wire                       s_tready;
    reg                        s_tlast;

    wire [TDATA_WIDTH-1:0]     m_tdata;
    wire [(TDATA_WIDTH/8)-1:0] m_tkeep;
    wire                       m_tvalid;
    reg                        m_tready;
    wire                       m_tlast;

    integer pass_count = 0;
    integer fail_count = 0;

    layer1_axis_stream_ingress #(.TDATA_WIDTH(TDATA_WIDTH)) dut (
        .clk(clk), .rst_n(rst_n),
        .s_tdata(s_tdata), .s_tkeep(s_tkeep), .s_tvalid(s_tvalid), .s_tready(s_tready), .s_tlast(s_tlast),
        .m_tdata(m_tdata), .m_tkeep(m_tkeep), .m_tvalid(m_tvalid), .m_tready(m_tready), .m_tlast(m_tlast)
    );

    always #(CLK_PERIOD/2) clk = ~clk;

    // ---------------- passive receive log ----------------
    reg [TDATA_WIDTH-1:0]     rx_data [0:255];
    reg [(TDATA_WIDTH/8)-1:0] rx_keep [0:255];
    reg                        rx_last [0:255];
    integer rx_count = 0;

    always @(posedge clk) begin
        if (m_tvalid && m_tready) begin
            rx_data[rx_count] <= m_tdata;
            rx_keep[rx_count] <= m_tkeep;
            rx_last[rx_count] <= m_tlast;
            rx_count          <= rx_count + 1;
        end
    end

    task reset_dut;
        begin
            rst_n = 0;
            s_tvalid = 0; s_tlast = 0; s_tdata = 0; s_tkeep = {(TDATA_WIDTH/8){1'b1}};
            m_tready = 1;
            repeat (3) @(posedge clk);
            rst_n = 1;
            @(posedge clk);
        end
    endtask

    task send_beat(input [TDATA_WIDTH-1:0] data, input last);
        begin
            @(negedge clk);
            s_tdata  = data;
            s_tkeep  = {(TDATA_WIDTH/8){1'b1}};
            s_tvalid = 1;
            s_tlast  = last;
            @(posedge clk);
            while (s_tready !== 1'b1) @(posedge clk);
            @(negedge clk);
            s_tvalid = 0;
            s_tlast  = 0;
        end
    endtask

    integer exp_idx = 0;
    task check_next(input [TDATA_WIDTH-1:0] exp_data, input exp_last, input [255:0] label);
        begin
            while (rx_count <= exp_idx) @(posedge clk);
            @(negedge clk);
            if (rx_data[exp_idx] === exp_data && rx_last[exp_idx] === exp_last)
                pass_count = pass_count + 1;
            else begin
                fail_count = fail_count + 1;
                $display("FAIL [%0s]: beat %0d mismatch", label, exp_idx);
            end
            exp_idx = exp_idx + 1;
        end
    endtask

    initial begin
        clk = 0;
        reset_dut;

        // -------- Test 1: basic in-order passthrough, 4 beats --------
        send_beat({16{32'h1111_0000}}, 0);
        send_beat({16{32'h1111_0001}}, 0);
        send_beat({16{32'h1111_0002}}, 0);
        send_beat({16{32'h1111_0003}}, 1);
        check_next({16{32'h1111_0000}}, 1'b0, "basic_beat0");
        check_next({16{32'h1111_0001}}, 1'b0, "basic_beat1");
        check_next({16{32'h1111_0002}}, 1'b0, "basic_beat2");
        check_next({16{32'h1111_0003}}, 1'b1, "basic_beat3");

        // -------- Test 2: continuous back-to-back throughput (no gaps).
        //                  Drives tvalid high across all 8 beats without
        //                  ever dropping it, changing tdata every cycle,
        //                  proving s_tready = m_tready|!m_tvalid actually
        //                  delivers full throughput and not just
        //                  gapped/task-paced transfers. --------
        begin : burst_test
            integer i, rx_before;
            rx_before = rx_count;
            @(negedge clk);
            s_tvalid = 1;
            s_tkeep  = {(TDATA_WIDTH/8){1'b1}};
            for (i = 0; i < 8; i = i + 1) begin
                s_tdata = {16{32'h2222_0000 + i}};
                s_tlast = (i == 7);
                @(posedge clk);
                // m_tready held high throughout -> s_tready should read 1
                // every single cycle here (zero-bubble claim under test).
                if (s_tready === 1'b1) pass_count = pass_count + 1;
                else begin fail_count = fail_count + 1; $display("FAIL [burst]: s_tready dropped mid-burst at beat %0d", i); end
                @(negedge clk);
            end
            s_tvalid = 0;
            s_tlast  = 0;

            // Drain and check all 8 landed, in order, 1-cycle-delayed.
            for (i = 0; i < 8; i = i + 1)
                check_next({16{32'h2222_0000 + i}}, (i == 7), "burst_beat");

            if ((rx_count - rx_before) == 8) pass_count = pass_count + 1;
            else begin fail_count = fail_count + 1; $display("FAIL [burst]: expected 8 beats, got %0d", rx_count - rx_before); end
        end

        // -------- Test 3: backpressure — m_tready held low for several
        //                  cycles after a beat is buffered. Verifies
        //                  m_tdata/tvalid hold stable and s_tready
        //                  correctly drops (buffer full, no drain). --------
        begin : backpressure_test
            integer r;
            m_tready = 0;
            @(negedge clk);
            s_tdata  = {16{32'h3333_0000}};
            s_tkeep  = {(TDATA_WIDTH/8){1'b1}};
            s_tvalid = 1;
            s_tlast  = 1'b0;
            @(posedge clk); // beat accepted into the register (buffer was empty)
            @(negedge clk);
            s_tvalid = 0;

            @(posedge clk);
            while (!m_tvalid) @(posedge clk);

            for (r = 0; r < 4; r = r + 1) begin
                @(negedge clk);
                if (m_tvalid === 1'b1 && m_tdata === {16{32'h3333_0000}})
                    pass_count = pass_count + 1;
                else begin fail_count = fail_count + 1; $display("FAIL [backpressure]: output did not hold stable while stalled"); end
                if (s_tready === 1'b0) pass_count = pass_count + 1;
                else begin fail_count = fail_count + 1; $display("FAIL [backpressure]: s_tready should be low (buffer full, consumer stalled)"); end
            end

            @(negedge clk);
            m_tready = 1;
            check_next({16{32'h3333_0000}}, 1'b0, "backpressure_release");
        end

        // -------- Test 4: reset mid-transfer clears cleanly --------
        @(negedge clk);
        s_tdata  = {16{32'h4444_0000}};
        s_tkeep  = {(TDATA_WIDTH/8){1'b1}};
        s_tvalid = 1;
        s_tlast  = 0;
        @(posedge clk);
        while (s_tready !== 1'b1) @(posedge clk);
        @(negedge clk);
        s_tvalid = 0;
        reset_dut;
        if (m_tvalid === 1'b0 && s_tready === 1'b1) pass_count = pass_count + 1;
        else begin fail_count = fail_count + 1; $display("FAIL: state not clean after mid-transfer reset"); end

        // Confirm fresh traffic still works post-reset.
        send_beat({16{32'h5555_0000}}, 1'b1);
        check_next({16{32'h5555_0000}}, 1'b1, "post_reset_recovery");

        $display("=================================================");
        $display("TESTS PASSED: %0d   TESTS FAILED: %0d", pass_count, fail_count);
        $display("=================================================");
        if (fail_count == 0) $display("RESULT: ALL TESTS PASSED");
        else                 $display("RESULT: FAILURES PRESENT");

        $finish;
    end

    initial begin
        $dumpfile("sim/dump_layer1_axis_stream_ingress.vcd");
        $dumpvars(0, tb_layer1_axis_stream_ingress);
    end

endmodule

sim/dump_layer1_axis_stream_ingress.vcd
$date
	Sat Sep 12 13:48:00 2026
$end
$version
	Icarus Verilog
$end
$timescale
	1ps
$end
$scope module tb_layer1_axis_stream_ingress $end
$var wire 1 ! s_tready $end
$var wire 1 " m_tvalid $end
$var wire 1 # m_tlast $end
$var wire 64 $ m_tkeep [63:0] $end
$var wire 512 % m_tdata [511:0] $end
$var parameter 32 & CLK_PERIOD $end
$var parameter 32 ' TDATA_WIDTH $end
$var reg 1 ( clk $end
$var reg 1 ) m_tready $end
$var reg 1 * rst_n $end
$var reg 512 + s_tdata [511:0] $end
$var reg 64 , s_tkeep [63:0] $end
$var reg 1 - s_tlast $end
$var reg 1 . s_tvalid $end
$var integer 32 / exp_idx [31:0] $end
$var integer 32 0 fail_count [31:0] $end
$var integer 32 1 pass_count [31:0] $end
$var integer 32 2 rx_count [31:0] $end
$scope module dut $end
$var wire 1 ( clk $end
$var wire 1 ) m_tready $end
$var wire 1 * rst_n $end
$var wire 512 3 s_tdata [511:0] $end
$var wire 64 4 s_tkeep [63:0] $end
$var wire 1 - s_tlast $end
$var wire 1 ! s_tready $end
$var wire 1 . s_tvalid $end
$var parameter 32 5 TDATA_WIDTH $end
$var reg 512 6 m_tdata [511:0] $end
$var reg 64 7 m_tkeep [63:0] $end
$var reg 1 # m_tlast $end
$var reg 1 " m_tvalid $end
$upscope $end
$scope begin backpressure_test $end
$var integer 32 8 r [31:0] $end
$upscope $end
$scope begin burst_test $end
$var integer 32 9 i [31:0] $end
$var integer 32 : rx_before [31:0] $end
$upscope $end
$scope task check_next $end
$var reg 512 ; exp_data [511:0] $end
$var reg 1 < exp_last $end
$var reg 256 = label [255:0] $end
$upscope $end
$scope task reset_dut $end
$upscope $end
$scope task send_beat $end
$var reg 512 > data [511:0] $end
$var reg 1 ? last $end
$upscope $end
$upscope $end
$enddefinitions $end
$comment Show the parameter values. $end
$dumpall
b1000000000 5
b1000000000 '
b1010 &
$end
#0
$dumpvars
x?
bx >
bx =
x<
bx ;
bx :
bx 9
bx 8
b0 7
b0 6
b1111111111111111111111111111111111111111111111111111111111111111 4
b0 3
b0 2
b0 1
b0 0
b0 /
0.
0-
b1111111111111111111111111111111111111111111111111111111111111111 ,
b0 +
0*
1)
0(
b0 %
b0 $
0#
0"
1!
$end
#5000
1(
#10000
0(
#15000
1(
#20000
0(
#25000
1*
1(
#30000
0(
#35000
0?
b10001000100010000000000000000000100010001000100000000000000000001000100010001000000000000000000010001000100010000000000000000000100010001000100000000000000000001000100010001000000000000000000010001000100010000000000000000000100010001000100000000000000000001000100010001000000000000000000010001000100010000000000000000000100010001000100000000000000000001000100010001000000000000000000010001000100010000000000000000000100010001000100000000000000000001000100010001000000000000000000010001000100010000000000000000 >
1(
#40000
1.
b10001000100010000000000000000000100010001000100000000000000000001000100010001000000000000000000010001000100010000000000000000000100010001000100000000000000000001000100010001000000000000000000010001000100010000000000000000000100010001000100000000000000000001000100010001000000000000000000010001000100010000000000000000000100010001000100000000000000000001000100010001000000000000000000010001000100010000000000000000000100010001000100000000000000000001000100010001000000000000000000010001000100010000000000000000 +
b10001000100010000000000000000000100010001000100000000000000000001000100010001000000000000000000010001000100010000000000000000000100010001000100000000000000000001000100010001000000000000000000010001000100010000000000000000000100010001000100000000000000000001000100010001000000000000000000010001000100010000000000000000000100010001000100000000000000000001000100010001000000000000000000010001000100010000000000000000000100010001000100000000000000000001000100010001000000000000000000010001000100010000000000000000 3
0(
#45000
b1111111111111111111111111111111111111111111111111111111111111111 $
b1111111111111111111111111111111111111111111111111111111111111111 7
b10001000100010000000000000000000100010001000100000000000000000001000100010001000000000000000000010001000100010000000000000000000100010001000100000000000000000001000100010001000000000000000000010001000100010000000000000000000100010001000100000000000000000001000100010001000000000000000000010001000100010000000000000000000100010001000100000000000000000001000100010001000000000000000000010001000100010000000000000000000100010001000100000000000000000001000100010001000000000000000000010001000100010000000000000000 %
b10001000100010000000000000000000100010001000100000000000000000001000100010001000000000000000000010001000100010000000000000000000100010001000100000000000000000001000100010001000000000000000000010001000100010000000000000000000100010001000100000000000000000001000100010001000000000000000000010001000100010000000000000000000100010001000100000000000000000001000100010001000000000000000000010001000100010000000000000000000100010001000100000000000000000001000100010001000000000000000000010001000100010000000000000000 6
1"
1(
#50000
b10001000100010000000000000001000100010001000100000000000000010001000100010001000000000000000100010001000100010000000000000001000100010001000100000000000000010001000100010001000000000000000100010001000100010000000000000001000100010001000100000000000000010001000100010001000000000000000100010001000100010000000000000001000100010001000100000000000000010001000100010001000000000000000100010001000100010000000000000001000100010001000100000000000000010001000100010001000000000000000100010001000100010000000000000001 >
0.
0(
#55000
0"
b1 2
1(
#60000
1.
b10001000100010000000000000001000100010001000100000000000000010001000100010001000000000000000100010001000100010000000000000001000100010001000100000000000000010001000100010001000000000000000100010001000100010000000000000001000100010001000100000000000000010001000100010001000000000000000100010001000100010000000000000001000100010001000100000000000000010001000100010001000000000000000100010001000100010000000000000001000100010001000100000000000000010001000100010001000000000000000100010001000100010000000000000001 +
b10001000100010000000000000001000100010001000100000000000000010001000100010001000000000000000100010001000100010000000000000001000100010001000100000000000000010001000100010001000000000000000100010001000100010000000000000001000100010001000100000000000000010001000100010001000000000000000100010001000100010000000000000001000100010001000100000000000000010001000100010001000000000000000100010001000100010000000000000001000100010001000100000000000000010001000100010001000000000000000100010001000100010000000000000001 3
0(
#65000
b10001000100010000000000000001000100010001000100000000000000010001000100010001000000000000000100010001000100010000000000000001000100010001000100000000000000010001000100010001000000000000000100010001000100010000000000000001000100010001000100000000000000010001000100010001000000000000000100010001000100010000000000000001000100010001000100000000000000010001000100010001000000000000000100010001000100010000000000000001000100010001000100000000000000010001000100010001000000000000000100010001000100010000000000000001 %
b10001000100010000000000000001000100010001000100000000000000010001000100010001000000000000000100010001000100010000000000000001000100010001000100000000000000010001000100010001000000000000000100010001000100010000000000000001000100010001000100000000000000010001000100010001000000000000000100010001000100010000000000000001000100010001000100000000000000010001000100010001000000000000000100010001000100010000000000000001000100010001000100000000000000010001000100010001000000000000000100010001000100010000000000000001 6
1"
1(
#70000
b10001000100010000000000000010000100010001000100000000000000100001000100010001000000000000001000010001000100010000000000000010000100010001000100000000000000100001000100010001000000000000001000010001000100010000000000000010000100010001000100000000000000100001000100010001000000000000001000010001000100010000000000000010000100010001000100000000000000100001000100010001000000000000001000010001000100010000000000000010000100010001000100000000000000100001000100010001000000000000001000010001000100010000000000000010 >
0.
0(
#75000
0"
b10 2
1(
#80000
1.
b10001000100010000000000000010000100010001000100000000000000100001000100010001000000000000001000010001000100010000000000000010000100010001000100000000000000100001000100010001000000000000001000010001000100010000000000000010000100010001000100000000000000100001000100010001000000000000001000010001000100010000000000000010000100010001000100000000000000100001000100010001000000000000001000010001000100010000000000000010000100010001000100000000000000100001000100010001000000000000001000010001000100010000000000000010 +
b10001000100010000000000000010000100010001000100000000000000100001000100010001000000000000001000010001000100010000000000000010000100010001000100000000000000100001000100010001000000000000001000010001000100010000000000000010000100010001000100000000000000100001000100010001000000000000001000010001000100010000000000000010000100010001000100000000000000100001000100010001000000000000001000010001000100010000000000000010000100010001000100000000000000100001000100010001000000000000001000010001000100010000000000000010 3
0(
#85000
b10001000100010000000000000010000100010001000100000000000000100001000100010001000000000000001000010001000100010000000000000010000100010001000100000000000000100001000100010001000000000000001000010001000100010000000000000010000100010001000100000000000000100001000100010001000000000000001000010001000100010000000000000010000100010001000100000000000000100001000100010001000000000000001000010001000100010000000000000010000100010001000100000000000000100001000100010001000000000000001000010001000100010000000000000010 %
b10001000100010000000000000010000100010001000100000000000000100001000100010001000000000000001000010001000100010000000000000010000100010001000100000000000000100001000100010001000000000000001000010001000100010000000000000010000100010001000100000000000000100001000100010001000000000000001000010001000100010000000000000010000100010001000100000000000000100001000100010001000000000000001000010001000100010000000000000010000100010001000100000000000000100001000100010001000000000000001000010001000100010000000000000010 6
1"
1(
#90000
1?
b10001000100010000000000000011000100010001000100000000000000110001000100010001000000000000001100010001000100010000000000000011000100010001000100000000000000110001000100010001000000000000001100010001000100010000000000000011000100010001000100000000000000110001000100010001000000000000001100010001000100010000000000000011000100010001000100000000000000110001000100010001000000000000001100010001000100010000000000000011000100010001000100000000000000110001000100010001000000000000001100010001000100010000000000000011 >
0.
0(
#95000
0"
b11 2
1(
#100000
1-
1.
b10001000100010000000000000011000100010001000100000000000000110001000100010001000000000000001100010001000100010000000000000011000100010001000100000000000000110001000100010001000000000000001100010001000100010000000000000011000100010001000100000000000000110001000100010001000000000000001100010001000100010000000000000011000100010001000100000000000000110001000100010001000000000000001100010001000100010000000000000011000100010001000100000000000000110001000100010001000000000000001100010001000100010000000000000011 +
b10001000100010000000000000011000100010001000100000000000000110001000100010001000000000000001100010001000100010000000000000011000100010001000100000000000000110001000100010001000000000000001100010001000100010000000000000011000100010001000100000000000000110001000100010001000000000000001100010001000100010000000000000011000100010001000100000000000000110001000100010001000000000000001100010001000100010000000000000011000100010001000100000000000000110001000100010001000000000000001100010001000100010000000000000011 3
0(
#105000
1#
b10001000100010000000000000011000100010001000100000000000000110001000100010001000000000000001100010001000100010000000000000011000100010001000100000000000000110001000100010001000000000000001100010001000100010000000000000011000100010001000100000000000000110001000100010001000000000000001100010001000100010000000000000011000100010001000100000000000000110001000100010001000000000000001100010001000100010000000000000011000100010001000100000000000000110001000100010001000000000000001100010001000100010000000000000011 %
b10001000100010000000000000011000100010001000100000000000000110001000100010001000000000000001100010001000100010000000000000011000100010001000100000000000000110001000100010001000000000000001100010001000100010000000000000011000100010001000100000000000000110001000100010001000000000000001100010001000100010000000000000011000100010001000100000000000000110001000100010001000000000000001100010001000100010000000000000011000100010001000100000000000000110001000100010001000000000000001100010001000100010000000000000011 6
1"
1(
#110000
b110001001100001011100110110100101100011010111110110001001100101011000010111010000110000 =
0<
b10001000100010000000000000000000100010001000100000000000000000001000100010001000000000000000000010001000100010000000000000000000100010001000100000000000000000001000100010001000000000000000000010001000100010000000000000000000100010001000100000000000000000001000100010001000000000000000000010001000100010000000000000000000100010001000100000000000000000001000100010001000000000000000000010001000100010000000000000000000100010001000100000000000000000001000100010001000000000000000000010001000100010000000000000000 ;
0-
0.
0(
#115000
0"
b100 2
1(
#120000
b110001001100001011100110110100101100011010111110110001001100101011000010111010000110001 =
b10001000100010000000000000001000100010001000100000000000000010001000100010001000000000000000100010001000100010000000000000001000100010001000100000000000000010001000100010001000000000000000100010001000100010000000000000001000100010001000100000000000000010001000100010001000000000000000100010001000100010000000000000001000100010001000100000000000000010001000100010001000000000000000100010001000100010000000000000001000100010001000100000000000000010001000100010001000000000000000100010001000100010000000000000001 ;
b1 /
b1 1
0(
#125000
1(
#130000
b110001001100001011100110110100101100011010111110110001001100101011000010111010000110010 =
b10001000100010000000000000010000100010001000100000000000000100001000100010001000000000000001000010001000100010000000000000010000100010001000100000000000000100001000100010001000000000000001000010001000100010000000000000010000100010001000100000000000000100001000100010001000000000000001000010001000100010000000000000010000100010001000100000000000000100001000100010001000000000000001000010001000100010000000000000010000100010001000100000000000000100001000100010001000000000000001000010001000100010000000000000010 ;
b10 /
b10 1
0(
#135000
1(
#140000
b110001001100001011100110110100101100011010111110110001001100101011000010111010000110011 =
1<
b10001000100010000000000000011000100010001000100000000000000110001000100010001000000000000001100010001000100010000000000000011000100010001000100000000000000110001000100010001000000000000001100010001000100010000000000000011000100010001000100000000000000110001000100010001000000000000001100010001000100010000000000000011000100010001000100000000000000110001000100010001000000000000001100010001000100010000000000000011000100010001000100000000000000110001000100010001000000000000001100010001000100010000000000000011 ;
b11 /
b11 1
0(
#145000
1(
#150000
b100 :
b100 /
b100 1
0(
#155000
1(
#160000
b100010001000100000000000000000001000100010001000000000000000000010001000100010000000000000000000100010001000100000000000000000001000100010001000000000000000000010001000100010000000000000000000100010001000100000000000000000001000100010001000000000000000000010001000100010000000000000000000100010001000100000000000000000001000100010001000000000000000000010001000100010000000000000000000100010001000100000000000000000001000100010001000000000000000000010001000100010000000000000000000100010001000100000000000000000 +
b100010001000100000000000000000001000100010001000000000000000000010001000100010000000000000000000100010001000100000000000000000001000100010001000000000000000000010001000100010000000000000000000100010001000100000000000000000001000100010001000000000000000000010001000100010000000000000000000100010001000100000000000000000001000100010001000000000000000000010001000100010000000000000000000100010001000100000000000000000001000100010001000000000000000000010001000100010000000000000000000100010001000100000000000000000 3
b0 9
1.
0(
#165000
0#
b100010001000100000000000000000001000100010001000000000000000000010001000100010000000000000000000100010001000100000000000000000001000100010001000000000000000000010001000100010000000000000000000100010001000100000000000000000001000100010001000000000000000000010001000100010000000000000000000100010001000100000000000000000001000100010001000000000000000000010001000100010000000000000000000100010001000100000000000000000001000100010001000000000000000000010001000100010000000000000000000100010001000100000000000000000 %
b100010001000100000000000000000001000100010001000000000000000000010001000100010000000000000000000100010001000100000000000000000001000100010001000000000000000000010001000100010000000000000000000100010001000100000000000000000001000100010001000000000000000000010001000100010000000000000000000100010001000100000000000000000001000100010001000000000000000000010001000100010000000000000000000100010001000100000000000000000001000100010001000000000000000000010001000100010000000000000000000100010001000100000000000000000 6
1"
b101 1
1(
#170000
b100010001000100000000000000001001000100010001000000000000000010010001000100010000000000000000100100010001000100000000000000001001000100010001000000000000000010010001000100010000000000000000100100010001000100000000000000001001000100010001000000000000000010010001000100010000000000000000100100010001000100000000000000001001000100010001000000000000000010010001000100010000000000000000100100010001000100000000000000001001000100010001000000000000000010010001000100010000000000000000100100010001000100000000000000001 +
b100010001000100000000000000001001000100010001000000000000000010010001000100010000000000000000100100010001000100000000000000001001000100010001000000000000000010010001000100010000000000000000100100010001000100000000000000001001000100010001000000000000000010010001000100010000000000000000100100010001000100000000000000001001000100010001000000000000000010010001000100010000000000000000100100010001000100000000000000001001000100010001000000000000000010010001000100010000000000000000100100010001000100000000000000001 3
b1 9
0(
#175000
b100010001000100000000000000001001000100010001000000000000000010010001000100010000000000000000100100010001000100000000000000001001000100010001000000000000000010010001000100010000000000000000100100010001000100000000000000001001000100010001000000000000000010010001000100010000000000000000100100010001000100000000000000001001000100010001000000000000000010010001000100010000000000000000100100010001000100000000000000001001000100010001000000000000000010010001000100010000000000000000100100010001000100000000000000001 %
b100010001000100000000000000001001000100010001000000000000000010010001000100010000000000000000100100010001000100000000000000001001000100010001000000000000000010010001000100010000000000000000100100010001000100000000000000001001000100010001000000000000000010010001000100010000000000000000100100010001000100000000000000001001000100010001000000000000000010010001000100010000000000000000100100010001000100000000000000001001000100010001000000000000000010010001000100010000000000000000100100010001000100000000000000001 6
b101 2
b110 1
1(
#180000
b100010001000100000000000000010001000100010001000000000000000100010001000100010000000000000001000100010001000100000000000000010001000100010001000000000000000100010001000100010000000000000001000100010001000100000000000000010001000100010001000000000000000100010001000100010000000000000001000100010001000100000000000000010001000100010001000000000000000100010001000100010000000000000001000100010001000100000000000000010001000100010001000000000000000100010001000100010000000000000001000100010001000100000000000000010 +
b100010001000100000000000000010001000100010001000000000000000100010001000100010000000000000001000100010001000100000000000000010001000100010001000000000000000100010001000100010000000000000001000100010001000100000000000000010001000100010001000000000000000100010001000100010000000000000001000100010001000100000000000000010001000100010001000000000000000100010001000100010000000000000001000100010001000100000000000000010001000100010001000000000000000100010001000100010000000000000001000100010001000100000000000000010 3
b10 9
0(
#185000
b100010001000100000000000000010001000100010001000000000000000100010001000100010000000000000001000100010001000100000000000000010001000100010001000000000000000100010001000100010000000000000001000100010001000100000000000000010001000100010001000000000000000100010001000100010000000000000001000100010001000100000000000000010001000100010001000000000000000100010001000100010000000000000001000100010001000100000000000000010001000100010001000000000000000100010001000100010000000000000001000100010001000100000000000000010 %
b100010001000100000000000000010001000100010001000000000000000100010001000100010000000000000001000100010001000100000000000000010001000100010001000000000000000100010001000100010000000000000001000100010001000100000000000000010001000100010001000000000000000100010001000100010000000000000001000100010001000100000000000000010001000100010001000000000000000100010001000100010000000000000001000100010001000100000000000000010001000100010001000000000000000100010001000100010000000000000001000100010001000100000000000000010 6
b110 2
b111 1
1(
#190000
b100010001000100000000000000011001000100010001000000000000000110010001000100010000000000000001100100010001000100000000000000011001000100010001000000000000000110010001000100010000000000000001100100010001000100000000000000011001000100010001000000000000000110010001000100010000000000000001100100010001000100000000000000011001000100010001000000000000000110010001000100010000000000000001100100010001000100000000000000011001000100010001000000000000000110010001000100010000000000000001100100010001000100000000000000011 +
b100010001000100000000000000011001000100010001000000000000000110010001000100010000000000000001100100010001000100000000000000011001000100010001000000000000000110010001000100010000000000000001100100010001000100000000000000011001000100010001000000000000000110010001000100010000000000000001100100010001000100000000000000011001000100010001000000000000000110010001000100010000000000000001100100010001000100000000000000011001000100010001000000000000000110010001000100010000000000000001100100010001000100000000000000011 3
b11 9
0(
#195000
b100010001000100000000000000011001000100010001000000000000000110010001000100010000000000000001100100010001000100000000000000011001000100010001000000000000000110010001000100010000000000000001100100010001000100000000000000011001000100010001000000000000000110010001000100010000000000000001100100010001000100000000000000011001000100010001000000000000000110010001000100010000000000000001100100010001000100000000000000011001000100010001000000000000000110010001000100010000000000000001100100010001000100000000000000011 %
b100010001000100000000000000011001000100010001000000000000000110010001000100010000000000000001100100010001000100000000000000011001000100010001000000000000000110010001000100010000000000000001100100010001000100000000000000011001000100010001000000000000000110010001000100010000000000000001100100010001000100000000000000011001000100010001000000000000000110010001000100010000000000000001100100010001000100000000000000011001000100010001000000000000000110010001000100010000000000000001100100010001000100000000000000011 6
b111 2
b1000 1
1(
#200000
b100010001000100000000000000100001000100010001000000000000001000010001000100010000000000000010000100010001000100000000000000100001000100010001000000000000001000010001000100010000000000000010000100010001000100000000000000100001000100010001000000000000001000010001000100010000000000000010000100010001000100000000000000100001000100010001000000000000001000010001000100010000000000000010000100010001000100000000000000100001000100010001000000000000001000010001000100010000000000000010000100010001000100000000000000100 +
b100010001000100000000000000100001000100010001000000000000001000010001000100010000000000000010000100010001000100000000000000100001000100010001000000000000001000010001000100010000000000000010000100010001000100000000000000100001000100010001000000000000001000010001000100010000000000000010000100010001000100000000000000100001000100010001000000000000001000010001000100010000000000000010000100010001000100000000000000100001000100010001000000000000001000010001000100010000000000000010000100010001000100000000000000100 3
b100 9
0(
#205000
b100010001000100000000000000100001000100010001000000000000001000010001000100010000000000000010000100010001000100000000000000100001000100010001000000000000001000010001000100010000000000000010000100010001000100000000000000100001000100010001000000000000001000010001000100010000000000000010000100010001000100000000000000100001000100010001000000000000001000010001000100010000000000000010000100010001000100000000000000100001000100010001000000000000001000010001000100010000000000000010000100010001000100000000000000100 %
b100010001000100000000000000100001000100010001000000000000001000010001000100010000000000000010000100010001000100000000000000100001000100010001000000000000001000010001000100010000000000000010000100010001000100000000000000100001000100010001000000000000001000010001000100010000000000000010000100010001000100000000000000100001000100010001000000000000001000010001000100010000000000000010000100010001000100000000000000100001000100010001000000000000001000010001000100010000000000000010000100010001000100000000000000100 6
b1000 2
b1001 1
1(
#210000
b100010001000100000000000000101001000100010001000000000000001010010001000100010000000000000010100100010001000100000000000000101001000100010001000000000000001010010001000100010000000000000010100100010001000100000000000000101001000100010001000000000000001010010001000100010000000000000010100100010001000100000000000000101001000100010001000000000000001010010001000100010000000000000010100100010001000100000000000000101001000100010001000000000000001010010001000100010000000000000010100100010001000100000000000000101 +
b100010001000100000000000000101001000100010001000000000000001010010001000100010000000000000010100100010001000100000000000000101001000100010001000000000000001010010001000100010000000000000010100100010001000100000000000000101001000100010001000000000000001010010001000100010000000000000010100100010001000100000000000000101001000100010001000000000000001010010001000100010000000000000010100100010001000100000000000000101001000100010001000000000000001010010001000100010000000000000010100100010001000100000000000000101 3
b101 9
0(
#215000
b100010001000100000000000000101001000100010001000000000000001010010001000100010000000000000010100100010001000100000000000000101001000100010001000000000000001010010001000100010000000000000010100100010001000100000000000000101001000100010001000000000000001010010001000100010000000000000010100100010001000100000000000000101001000100010001000000000000001010010001000100010000000000000010100100010001000100000000000000101001000100010001000000000000001010010001000100010000000000000010100100010001000100000000000000101 %
b100010001000100000000000000101001000100010001000000000000001010010001000100010000000000000010100100010001000100000000000000101001000100010001000000000000001010010001000100010000000000000010100100010001000100000000000000101001000100010001000000000000001010010001000100010000000000000010100100010001000100000000000000101001000100010001000000000000001010010001000100010000000000000010100100010001000100000000000000101001000100010001000000000000001010010001000100010000000000000010100100010001000100000000000000101 6
b1001 2
b1010 1
1(
