rtl/layer4_flit_to_phy_lanes.v
// =============================================================
// layer4_flit_to_phy_lanes.v
//
// Layer 4 (PCIe Protocol-to-PHY Layer) per the SARCathon reference
// architecture:
//
//   FLIT (256B data + 32-bit CRC) --> [this module] --> 4-lane
//   parallel symbol bus to analog PHY [To Multi-Lane SerDes]
//
// Behavior:
//   - Consumes one FLIT (2048-bit data + 32-bit CRC = 2080 bits)
//     from the Link Layer.
//   - Splits the 2080-bit payload into 1040 two-bit symbols.
//   - Round-robin striping across 4 lanes: symbol i -> lane (i%4),
//     position (i/4) within that lane. 1040/4 = 260 symbols/lane
//     exactly (2080 is lane- and symbol-aligned by construction,
//     since FLIT size and lane count were chosen to divide evenly).
//   - Each 2-bit symbol is Gray-coded (00->00, 01->01, 10->11,
//     11->10) before being placed on the lane bus, matching the
//     "Gray Coding & PAM4 Mapping (2 bits -> 1 symbol)" step in
//     the block diagram. The mapped 2-bit code is what a PAM4
//     driver would decode into one of 4 voltage levels; the
//     analog level generation itself is out of scope for RTL sim.
//
// This module presents each lane's full symbol burst for one FLIT
// as a single wide parallel word (520 bits = 260 symbols x 2 bits),
// valid/ready handshaked, rather than serializing lane-by-lane —
// serialization to the SerDes is a mechanical next step once a
// PHY model exists to serialize into.
// =============================================================

module layer4_flit_to_phy_lanes #(
    parameter DATA_BITS  = 2048,
    parameter CRC_BITS   = 32,
    parameter NUM_LANES  = 4,
    parameter SYM_BITS   = 2
)(
    input                              clk,
    input                              rst_n,

    // ---------------- FLIT input (from Link Layer) ----------------
    input      [DATA_BITS-1:0]         s_flit_data,
    input      [CRC_BITS-1:0]          s_flit_crc,
    input                              s_flit_valid,
    output reg                         s_flit_ready,

    // ---------------- Lane-striped symbol output ----------------
    output reg [((DATA_BITS+CRC_BITS)/NUM_LANES)-1:0] m_lane0_data,
    output reg [((DATA_BITS+CRC_BITS)/NUM_LANES)-1:0] m_lane1_data,
    output reg [((DATA_BITS+CRC_BITS)/NUM_LANES)-1:0] m_lane2_data,
    output reg [((DATA_BITS+CRC_BITS)/NUM_LANES)-1:0] m_lane3_data,
    output reg                         m_lane_valid,
    input                              m_lane_ready
);

    localparam TOTAL_BITS      = DATA_BITS + CRC_BITS;              // 2080
    localparam TOTAL_SYMBOLS   = TOTAL_BITS / SYM_BITS;              // 1040
    localparam LANE_BITS       = TOTAL_BITS / NUM_LANES;             // 520

    // Sanity checks on parameterization (elaboration-time).
    // Widths must divide evenly for the round-robin scheme below.
    initial begin
        if (TOTAL_BITS % SYM_BITS != 0)
            $fatal(1, "layer4_flit_to_phy_lanes: TOTAL_BITS must be a multiple of SYM_BITS");
        if (TOTAL_SYMBOLS % NUM_LANES != 0)
            $fatal(1, "layer4_flit_to_phy_lanes: TOTAL_SYMBOLS must be a multiple of NUM_LANES");
    end

    localparam ACCUM   = 2'd0,
               STRIPE   = 2'd1,
               PRESENT  = 2'd2;

    reg [1:0]              state;
    reg [TOTAL_BITS-1:0]   combined_reg;

    // Standard 2-bit Gray code: 0->00, 1->01, 2->11, 3->10
    function [SYM_BITS-1:0] gray_encode;
        input [SYM_BITS-1:0] val;
        begin
            gray_encode = {val[1], val[1] ^ val[0]};
        end
    endfunction

    always @(posedge clk or negedge rst_n) begin
        if (!rst_n) begin
            state         <= ACCUM;
            s_flit_ready  <= 1'b1;
            combined_reg  <= {TOTAL_BITS{1'b0}};
            m_lane0_data  <= {LANE_BITS{1'b0}};
            m_lane1_data  <= {LANE_BITS{1'b0}};
            m_lane2_data  <= {LANE_BITS{1'b0}};
            m_lane3_data  <= {LANE_BITS{1'b0}};
            m_lane_valid  <= 1'b0;
        end else begin
            case (state)

                ACCUM: begin
                    s_flit_ready <= 1'b1;
                    if (s_flit_valid && s_flit_ready) begin
                        // CRC placed at the top of the combined word so
                        // symbol 0 is the LSB of the FLIT data — matches
                        // the golden model used in verification.
                        combined_reg <= {s_flit_crc, s_flit_data};
                        s_flit_ready <= 1'b0;
                        state        <= STRIPE;
                    end
                end

                STRIPE: begin
                    integer sym_i, lane, pos;
                    reg [SYM_BITS-1:0] raw_sym, gray_sym;
                    for (sym_i = 0; sym_i < TOTAL_SYMBOLS; sym_i = sym_i + 1) begin
                        lane    = sym_i % NUM_LANES;
                        pos     = sym_i / NUM_LANES;
                        raw_sym = combined_reg[sym_i*SYM_BITS +: SYM_BITS];
                        gray_sym = gray_encode(raw_sym);
                        case (lane)
                            0: m_lane0_data[pos*SYM_BITS +: SYM_BITS] <= gray_sym;
                            1: m_lane1_data[pos*SYM_BITS +: SYM_BITS] <= gray_sym;
                            2: m_lane2_data[pos*SYM_BITS +: SYM_BITS] <= gray_sym;
                            3: m_lane3_data[pos*SYM_BITS +: SYM_BITS] <= gray_sym;
                        endcase
                    end
                    m_lane_valid <= 1'b1;
                    state        <= PRESENT;
                end

                PRESENT: begin
                    if (m_lane_valid && m_lane_ready) begin
                        m_lane_valid <= 1'b0;
                        s_flit_ready <= 1'b1;
                        state        <= ACCUM;
                    end
                end

                default: state <= ACCUM;

            endcase
        end
    end

endmodule

tb/tb_layer4_flit_to_phy_lanes.v
`timescale 1ns/1ps

module tb_layer4_flit_to_phy_lanes;

    localparam DATA_BITS = 2048;
    localparam CRC_BITS  = 32;
    localparam NUM_LANES = 4;
    localparam SYM_BITS  = 2;
    localparam TOTAL_BITS    = DATA_BITS + CRC_BITS;   // 2080
    localparam TOTAL_SYMBOLS = TOTAL_BITS / SYM_BITS;  // 1040
    localparam LANE_BITS     = TOTAL_BITS / NUM_LANES; // 520
    localparam CLK_PERIOD = 10;

    reg clk, rst_n;
    reg  [DATA_BITS-1:0] s_flit_data;
    reg  [CRC_BITS-1:0]  s_flit_crc;
    reg                  s_flit_valid;
    wire                 s_flit_ready;

    wire [LANE_BITS-1:0] m_lane0_data, m_lane1_data, m_lane2_data, m_lane3_data;
    wire                 m_lane_valid;
    reg                  m_lane_ready;

    integer pass_count = 0;
    integer fail_count = 0;

    layer4_flit_to_phy_lanes #(
        .DATA_BITS(DATA_BITS), .CRC_BITS(CRC_BITS),
        .NUM_LANES(NUM_LANES), .SYM_BITS(SYM_BITS)
    ) dut (
        .clk(clk), .rst_n(rst_n),
        .s_flit_data(s_flit_data), .s_flit_crc(s_flit_crc), .s_flit_valid(s_flit_valid), .s_flit_ready(s_flit_ready),
        .m_lane0_data(m_lane0_data), .m_lane1_data(m_lane1_data),
        .m_lane2_data(m_lane2_data), .m_lane3_data(m_lane3_data),
        .m_lane_valid(m_lane_valid), .m_lane_ready(m_lane_ready)
    );

    always #(CLK_PERIOD/2) clk = ~clk;

    // ---------------- golden reference model ----------------
    // Explicit lookup table rather than the DUT's XOR formula
    // ({val[1], val[1]^val[0]}) — same standard Gray-code mapping,
    // written a structurally different way so the two aren't just
    // the same expression typed twice.
    function [SYM_BITS-1:0] gray_ref;
        input [SYM_BITS-1:0] val;
        begin
            case (val)
                2'b00: gray_ref = 2'b00;
                2'b01: gray_ref = 2'b01;
                2'b10: gray_ref = 2'b11;
                2'b11: gray_ref = 2'b10;
            endcase
        end
    endfunction

    task reset_dut;
        begin
            rst_n = 0;
            s_flit_valid = 0;
            s_flit_data  = 0;
            s_flit_crc   = 0;
            m_lane_ready = 1;
            repeat (3) @(posedge clk);
            rst_n = 1;
            @(posedge clk);
        end
    endtask

    task send_flit(input [DATA_BITS-1:0] data, input [CRC_BITS-1:0] crc);
        begin
            @(negedge clk);
            s_flit_data  = data;
            s_flit_crc   = crc;
            s_flit_valid = 1;
            @(posedge clk);
            while (s_flit_ready !== 1'b1) @(posedge clk);
            @(negedge clk);
            s_flit_valid = 0;
        end
    endtask

    task check_lanes(input [DATA_BITS-1:0] data, input [CRC_BITS-1:0] crc, input [255:0] label);
        reg [TOTAL_BITS-1:0] combined;
        reg [LANE_BITS-1:0]  exp_lane [0:3];
        integer sym_i, lane, pos;
        reg [SYM_BITS-1:0] raw_sym, gray_sym;
        begin
            combined = {crc, data};
            for (sym_i = 0; sym_i < TOTAL_SYMBOLS; sym_i = sym_i + 1) begin
                lane = sym_i % NUM_LANES;
                pos  = sym_i / NUM_LANES;
                raw_sym  = combined[sym_i*SYM_BITS +: SYM_BITS];
                gray_sym = gray_ref(raw_sym);
                exp_lane[lane][pos*SYM_BITS +: SYM_BITS] = gray_sym;
            end

            @(posedge clk);
            while (!m_lane_valid) @(posedge clk);
            @(negedge clk);

            if (m_lane0_data === exp_lane[0]) pass_count = pass_count + 1;
            else begin fail_count = fail_count + 1; $display("FAIL [%0s]: lane0 mismatch", label); end

            if (m_lane1_data === exp_lane[1]) pass_count = pass_count + 1;
            else begin fail_count = fail_count + 1; $display("FAIL [%0s]: lane1 mismatch", label); end

            if (m_lane2_data === exp_lane[2]) pass_count = pass_count + 1;
            else begin fail_count = fail_count + 1; $display("FAIL [%0s]: lane2 mismatch", label); end

            if (m_lane3_data === exp_lane[3]) pass_count = pass_count + 1;
            else begin fail_count = fail_count + 1; $display("FAIL [%0s]: lane3 mismatch", label); end

            @(posedge clk);
        end
    endtask

    initial begin
        clk = 0;
        reset_dut;

        // -------- Test 1: all-zero FLIT (every symbol = 00 -> gray 00) --------
        send_flit({DATA_BITS{1'b0}}, {CRC_BITS{1'b0}});
        check_lanes({DATA_BITS{1'b0}}, {CRC_BITS{1'b0}}, "all_zero");

        // -------- Test 2: all-one FLIT (every symbol = 11 -> gray 10) --------
        send_flit({DATA_BITS{1'b1}}, {CRC_BITS{1'b1}});
        check_lanes({DATA_BITS{1'b1}}, {CRC_BITS{1'b1}}, "all_one");

        // -------- Test 3: known symbol-value counter pattern to verify
        //                  striping ORDER, not just gray-code correctness.
        //                  Each 2-bit slot i holds (i % 4), so lane
        //                  assignment can be checked position-by-position. --------
        begin : gen_counter_pattern
            reg [DATA_BITS-1:0] cdata;
            reg [CRC_BITS-1:0]  ccrc;
            integer i;
            reg [TOTAL_BITS-1:0] full;
            for (i = 0; i < TOTAL_SYMBOLS; i = i + 1)
                full[i*SYM_BITS +: SYM_BITS] = i % 4;
            ccrc  = full[TOTAL_BITS-1 -: CRC_BITS];
            cdata = full[DATA_BITS-1:0];
            send_flit(cdata, ccrc);
            check_lanes(cdata, ccrc, "counter_pattern");
        end

        // -------- Test 4: alternating 0xA5.../0x5A... pattern --------
        send_flit({(DATA_BITS/8){8'hA5}}, {(CRC_BITS/8){8'h5A}});
        check_lanes({(DATA_BITS/8){8'hA5}}, {(CRC_BITS/8){8'h5A}}, "alternating_pattern");

        // -------- Test 5: back-to-back FLITs (no idle cycles between) --------
        send_flit({DATA_BITS{1'b0}}, 32'hDEAD_BEEF);
        check_lanes({DATA_BITS{1'b0}}, 32'hDEAD_BEEF, "back_to_back_1");
        send_flit({DATA_BITS{1'b1}}, 32'hCAFE_F00D);
        check_lanes({DATA_BITS{1'b1}}, 32'hCAFE_F00D, "back_to_back_2");

        // -------- Test 6: backpressure — m_lane_ready held low for several
        //                  cycles after the lane outputs go valid. Verifies
        //                  the striped lane data holds stable while stalled
        //                  and s_flit_ready correctly stays low (no new FLIT
        //                  accepted) until the stall is released. --------
        begin : backpressure_test
            reg [TOTAL_BITS-1:0] combined_bp;
            reg [LANE_BITS-1:0]  exp_lane_bp [0:3];
            integer sym_i, lane, pos, r;
            reg [SYM_BITS-1:0] raw_sym, gray_sym;

            combined_bp = {32'h1357_9BDF, {(DATA_BITS/8){8'h3C}}};
            for (sym_i = 0; sym_i < TOTAL_SYMBOLS; sym_i = sym_i + 1) begin
                lane = sym_i % NUM_LANES;
                pos  = sym_i / NUM_LANES;
                raw_sym  = combined_bp[sym_i*SYM_BITS +: SYM_BITS];
                gray_sym = gray_ref(raw_sym);
                exp_lane_bp[lane][pos*SYM_BITS +: SYM_BITS] = gray_sym;
            end

            m_lane_ready = 0; // stall before the FLIT even arrives
            @(negedge clk);
            s_flit_data  = {(DATA_BITS/8){8'h3C}};
            s_flit_crc   = 32'h1357_9BDF;
            s_flit_valid = 1;
            @(posedge clk);
            while (s_flit_ready !== 1'b1) @(posedge clk);
            @(negedge clk);
            s_flit_valid = 0;

            @(posedge clk);
            while (!m_lane_valid) @(posedge clk);

            for (r = 0; r < 5; r = r + 1) begin
                @(negedge clk);
                if (m_lane_valid === 1'b1 &&
                    m_lane0_data === exp_lane_bp[0] && m_lane1_data === exp_lane_bp[1] &&
                    m_lane2_data === exp_lane_bp[2] && m_lane3_data === exp_lane_bp[3])
                    pass_count = pass_count + 1;
                else begin
                    fail_count = fail_count + 1;
                    $display("FAIL [backpressure]: lane outputs did not hold stable while stalled");
                end
                if (s_flit_ready === 1'b0) pass_count = pass_count + 1;
                else begin fail_count = fail_count + 1; $display("FAIL [backpressure]: s_flit_ready should stay low while stalled"); end
            end

            @(negedge clk);
            m_lane_ready = 1; // release
            check_lanes({(DATA_BITS/8){8'h3C}}, 32'h1357_9BDF, "backpressure_release");
        end

        // -------- Test 7: reset mid-stripe clears state cleanly --------
        @(negedge clk);
        s_flit_data  = {DATA_BITS{1'b1}};
        s_flit_crc   = 32'hFFFF_FFFF;
        s_flit_valid = 1;
        @(posedge clk);
        while (s_flit_ready !== 1'b1) @(posedge clk);
        @(negedge clk);
        s_flit_valid = 0;
        reset_dut;
        if (s_flit_ready === 1'b1 && m_lane_valid === 1'b0) pass_count = pass_count + 1;
        else begin fail_count = fail_count + 1; $display("FAIL: state not clean after mid-stripe reset"); end

        $display("=================================================");
        $display("TESTS PASSED: %0d   TESTS FAILED: %0d", pass_count, fail_count);
        $display("=================================================");
        if (fail_count == 0)
            $display("RESULT: ALL TESTS PASSED");
        else
            $display("RESULT: FAILURES PRESENT");

        $finish;
    end

    initial begin
        $dumpfile("sim/dump_layer4_flit_to_phy_lanes.vcd");
        $dumpvars(0, tb_layer4_flit_to_phy_lanes);
    end

endmodule

results/dump_layer4_flit_to_phy_lanes.vcd
$date
	Sat Sep 12 07:51:02 2026
$end
$version
	Icarus Verilog
$end
$timescale
	1ps
$end
$scope module tb_layer4_flit_to_phy_lanes $end
$var wire 1 ! s_flit_ready $end
$var wire 1 " m_lane_valid $end
$var wire 520 # m_lane3_data [519:0] $end
$var wire 520 $ m_lane2_data [519:0] $end
$var wire 520 % m_lane1_data [519:0] $end
$var wire 520 & m_lane0_data [519:0] $end
$var parameter 32 ' CLK_PERIOD $end
$var parameter 32 ( CRC_BITS $end
$var parameter 32 ) DATA_BITS $end
$var parameter 33 * LANE_BITS $end
$var parameter 32 + NUM_LANES $end
$var parameter 32 , SYM_BITS $end
$var parameter 33 - TOTAL_BITS $end
$var parameter 33 . TOTAL_SYMBOLS $end
$var reg 1 / clk $end
$var reg 1 0 m_lane_ready $end
$var reg 1 1 rst_n $end
$var reg 32 2 s_flit_crc [31:0] $end
$var reg 2048 3 s_flit_data [2047:0] $end
$var reg 1 4 s_flit_valid $end
$var integer 32 5 fail_count [31:0] $end
$var integer 32 6 pass_count [31:0] $end
$scope function gray_ref $end
$var reg 2 7 val [1:0] $end
$upscope $end
$scope module dut $end
$var wire 1 / clk $end
$var wire 1 0 m_lane_ready $end
$var wire 1 1 rst_n $end
$var wire 32 8 s_flit_crc [31:0] $end
$var wire 2048 9 s_flit_data [2047:0] $end
$var wire 1 4 s_flit_valid $end
$var parameter 2 : ACCUM $end
$var parameter 32 ; CRC_BITS $end
$var parameter 32 < DATA_BITS $end
$var parameter 33 = LANE_BITS $end
$var parameter 32 > NUM_LANES $end
$var parameter 2 ? PRESENT $end
$var parameter 2 @ STRIPE $end
$var parameter 32 A SYM_BITS $end
$var parameter 33 B TOTAL_BITS $end
$var parameter 33 C TOTAL_SYMBOLS $end
$var reg 2080 D combined_reg [2079:0] $end
$var reg 520 E m_lane0_data [519:0] $end
$var reg 520 F m_lane1_data [519:0] $end
$var reg 520 G m_lane2_data [519:0] $end
$var reg 520 H m_lane3_data [519:0] $end
$var reg 1 " m_lane_valid $end
$var reg 1 ! s_flit_ready $end
$var reg 2 I state [1:0] $end
$scope function gray_encode $end
$var reg 2 J val [1:0] $end
$upscope $end
$scope begin $unm_blk_24 $end
$var reg 2 K gray_sym [1:0] $end
$var reg 2 L raw_sym [1:0] $end
$var integer 32 M lane [31:0] $end
$var integer 32 N pos [31:0] $end
$var integer 32 O sym_i [31:0] $end
$upscope $end
$upscope $end
$scope begin backpressure_test $end
$var reg 2080 P combined_bp [2079:0] $end
$var reg 2 Q gray_sym [1:0] $end
$var reg 2 R raw_sym [1:0] $end
$var integer 32 S lane [31:0] $end
$var integer 32 T pos [31:0] $end
$var integer 32 U r [31:0] $end
$var integer 32 V sym_i [31:0] $end
$upscope $end
$scope begin gen_counter_pattern $end
$var reg 32 W ccrc [31:0] $end
$var reg 2048 X cdata [2047:0] $end
$var reg 2080 Y full [2079:0] $end
$var integer 32 Z i [31:0] $end
$upscope $end
$scope task check_lanes $end
$var reg 2080 [ combined [2079:0] $end
$var reg 32 \ crc [31:0] $end
$var reg 2048 ] data [2047:0] $end
$var reg 2 ^ gray_sym [1:0] $end
$var reg 256 _ label [255:0] $end
$var reg 2 ` raw_sym [1:0] $end
$var integer 32 a lane [31:0] $end
$var integer 32 b pos [31:0] $end
$var integer 32 c sym_i [31:0] $end
$upscope $end
$scope task reset_dut $end
$upscope $end
$scope task send_flit $end
$var reg 32 d crc [31:0] $end
$var reg 2048 e data [2047:0] $end
$upscope $end
$upscope $end
$enddefinitions $end
$comment Show the parameter values. $end
$dumpall
b10000010000 C
b100000100000 B
b10 A
b1 @
b10 ?
b100 >
b1000001000 =
b100000000000 <
b100000 ;
b0 :
b10000010000 .
b100000100000 -
b10 ,
b100 +
b1000001000 *
b100000000000 )
b100000 (
b1010 '
$end
#0
$dumpvars
bx e
bx d
bx c
bx b
bx a
bx `
bx _
bx ^
bx ]
bx \
bx [
bx Z
bx Y
bx X
bx W
bx V
bx U
bx T
bx S
bx R
bx Q
bx P
bx O
bx N
bx M
bx L
bx K
bx J
b0 I
b0 H
b0 G
b0 F
b0 E
b0 D
b0 9
b0 8
bx 7
b0 6
b0 5
04
b0 3
b0 2
01
10
0/
b0 &
b0 %
b0 $
b0 #
0"
1!
$end
#5000
1/
#10000
0/
#15000
1/
#20000
0/
#25000
11
1/
#30000
0/
#35000
b0 d
b0 e
1/
#40000
14
0/
#45000
b1 I
0!
1/
#50000
b0 ^
b0 7
b0 `
b100000011 b
b11 a
b10000010000 c
b0 [
b110000101101100011011000101111101111010011001010111001001101111 _
b0 \
b0 ]
04
0/
#55000
b10 I
1"
b0 K
b0 J
b0 L
b100000011 N
b11 M
b10000010000 O
1/
#60000
0/
#65000
b0 I
1!
0"
1/
#70000
b100 6
0/
#75000
b11111111111111111111111111111111 d
b11111111111111111111111111111111111111111111111111111111111111111111111111111111111111111111111111111111111111111111111111111111111111111111111111111111111111111111111111111111111111111111111111111111111111111111111111111111111111111111111111111111111111111111111111111111111111111111111111111111111111111111111111111111111111111111111111111111111111111111111111111111111111111111111111111111111111111111111111111111111111111111111111111111111111111111111111111111111111111111111111111111111111111111111111111111111111111111111111111111111111111111111111111111111111111111111111111111111111111111111111111111111111111111111111111111111111111111111111111111111111111111111111111111111111111111111111111111111111111111111111111111111111111111111111111111111111111111111111111111111111111111111111111111111111111111111111111111111111111111111111111111111111111111111111111111111111111111111111111111111111111111111111111111111111111111111111111111111111111111111111111111111111111111111111111111111111111111111111111111111111111111111111111111111111111111111111111111111111111111111111111111111111111111111111111111111111111111111111111111111111111111111111111111111111111111111111111111111111111111111111111111111111111111111111111111111111111111111111111111111111111111111111111111111111111111111111111111111111111111111111111111111111111111111111111111111111111111111111111111111111111111111111111111111111111111111111111111111111111111111111111111111111111111111111111111111111111111111111111111111111111111111111111111111111111111111111111111111111111111111111111111111111111111111111111111111111111111111111111111111111111111111111111111111111111111111111111111111111111111111111111111111111111111111111111111111111111111111111111111111111111111111111111111111111111111111111111111111111111111111111111111111111111111111111111111111111111111111111111111111111111111111111111111111111111111111111111111111111111111111111111111111111111111111111111111111111111111111111111111111111111111111111111111111111111111111111111111111111111111111111111111 e
1/
#80000
14
b11111111111111111111111111111111 2
b11111111111111111111111111111111 8
b11111111111111111111111111111111111111111111111111111111111111111111111111111111111111111111111111111111111111111111111111111111111111111111111111111111111111111111111111111111111111111111111111111111111111111111111111111111111111111111111111111111111111111111111111111111111111111111111111111111111111111111111111111111111111111111111111111111111111111111111111111111111111111111111111111111111111111111111111111111111111111111111111111111111111111111111111111111111111111111111111111111111111111111111111111111111111111111111111111111111111111111111111111111111111111111111111111111111111111111111111111111111111111111111111111111111111111111111111111111111111111111111111111111111111111111111111111111111111111111111111111111111111111111111111111111111111111111111111111111111111111111111111111111111111111111111111111111111111111111111111111111111111111111111111111111111111111111111111111111111111111111111111111111111111111111111111111111111111111111111111111111111111111111111111111111111111111111111111111111111111111111111111111111111111111111111111111111111111111111111111111111111111111111111111111111111111111111111111111111111111111111111111111111111111111111111111111111111111111111111111111111111111111111111111111111111111111111111111111111111111111111111111111111111111111111111111111111111111111111111111111111111111111111111111111111111111111111111111111111111111111111111111111111111111111111111111111111111111111111111111111111111111111111111111111111111111111111111111111111111111111111111111111111111111111111111111111111111111111111111111111111111111111111111111111111111111111111111111111111111111111111111111111111111111111111111111111111111111111111111111111111111111111111111111111111111111111111111111111111111111111111111111111111111111111111111111111111111111111111111111111111111111111111111111111111111111111111111111111111111111111111111111111111111111111111111111111111111111111111111111111111111111111111111111111111111111111111111111111111111111111111111111111111111111111111111111111111111111111111111111111111 3
b11111111111111111111111111111111111111111111111111111111111111111111111111111111111111111111111111111111111111111111111111111111111111111111111111111111111111111111111111111111111111111111111111111111111111111111111111111111111111111111111111111111111111111111111111111111111111111111111111111111111111111111111111111111111111111111111111111111111111111111111111111111111111111111111111111111111111111111111111111111111111111111111111111111111111111111111111111111111111111111111111111111111111111111111111111111111111111111111111111111111111111111111111111111111111111111111111111111111111111111111111111111111111111111111111111111111111111111111111111111111111111111111111111111111111111111111111111111111111111111111111111111111111111111111111111111111111111111111111111111111111111111111111111111111111111111111111111111111111111111111111111111111111111111111111111111111111111111111111111111111111111111111111111111111111111111111111111111111111111111111111111111111111111111111111111111111111111111111111111111111111111111111111111111111111111111111111111111111111111111111111111111111111111111111111111111111111111111111111111111111111111111111111111111111111111111111111111111111111111111111111111111111111111111111111111111111111111111111111111111111111111111111111111111111111111111111111111111111111111111111111111111111111111111111111111111111111111111111111111111111111111111111111111111111111111111111111111111111111111111111111111111111111111111111111111111111111111111111111111111111111111111111111111111111111111111111111111111111111111111111111111111111111111111111111111111111111111111111111111111111111111111111111111111111111111111111111111111111111111111111111111111111111111111111111111111111111111111111111111111111111111111111111111111111111111111111111111111111111111111111111111111111111111111111111111111111111111111111111111111111111111111111111111111111111111111111111111111111111111111111111111111111111111111111111111111111111111111111111111111111111111111111111111111111111111111111111111111111111111111111111111111 9
0/
#85000
b1 I
0!
b1111111111111111111111111111111111111111111111111111111111111111111111111111111111111111111111111111111111111111111111111111111111111111111111111111111111111111111111111111111111111111111111111111111111111111111111111111111111111111111111111111111111111111111111111111111111111111111111111111111111111111111111111111111111111111111111111111111111111111111111111111111111111111111111111111111111111111111111111111111111111111111111111111111111111111111111111111111111111111111111111111111111111111111111111111111111111111111111111111111111111111111111111111111111111111111111111111111111111111111111111111111111111111111111111111111111111111111111111111111111111111111111111111111111111111111111111111111111111111111111111111111111111111111111111111111111111111111111111111111111111111111111111111111111111111111111111111111111111111111111111111111111111111111111111111111111111111111111111111111111111111111111111111111111111111111111111111111111111111111111111111111111111111111111111111111111111111111111111111111111111111111111111111111111111111111111111111111111111111111111111111111111111111111111111111111111111111111111111111111111111111111111111111111111111111111111111111111111111111111111111111111111111111111111111111111111111111111111111111111111111111111111111111111111111111111111111111111111111111111111111111111111111111111111111111111111111111111111111111111111111111111111111111111111111111111111111111111111111111111111111111111111111111111111111111111111111111111111111111111111111111111111111111111111111111111111111111111111111111111111111111111111111111111111111111111111111111111111111111111111111111111111111111111111111111111111111111111111111111111111111111111111111111111111111111111111111111111111111111111111111111111111111111111111111111111111111111111111111111111111111111111111111111111111111111111111111111111111111111111111111111111111111111111111111111111111111111111111111111111111111111111111111111111111111111111111111111111111111111111111111111111111111111111111111111111111111111111111111111111111111111111111111111111111111111111111111111 D
1/
#90000
b10 ^
b11 7
b11 `
b100000011 b
b11 a
b10000010000 c
b1111111111111111111111111111111111111111111111111111111111111111111111111111111111111111111111111111111111111111111111111111111111111111111111111111111111111111111111111111111111111111111111111111111111111111111111111111111111111111111111111111111111111111111111111111111111111111111111111111111111111111111111111111111111111111111111111111111111111111111111111111111111111111111111111111111111111111111111111111111111111111111111111111111111111111111111111111111111111111111111111111111111111111111111111111111111111111111111111111111111111111111111111111111111111111111111111111111111111111111111111111111111111111111111111111111111111111111111111111111111111111111111111111111111111111111111111111111111111111111111111111111111111111111111111111111111111111111111111111111111111111111111111111111111111111111111111111111111111111111111111111111111111111111111111111111111111111111111111111111111111111111111111111111111111111111111111111111111111111111111111111111111111111111111111111111111111111111111111111111111111111111111111111111111111111111111111111111111111111111111111111111111111111111111111111111111111111111111111111111111111111111111111111111111111111111111111111111111111111111111111111111111111111111111111111111111111111111111111111111111111111111111111111111111111111111111111111111111111111111111111111111111111111111111111111111111111111111111111111111111111111111111111111111111111111111111111111111111111111111111111111111111111111111111111111111111111111111111111111111111111111111111111111111111111111111111111111111111111111111111111111111111111111111111111111111111111111111111111111111111111111111111111111111111111111111111111111111111111111111111111111111111111111111111111111111111111111111111111111111111111111111111111111111111111111111111111111111111111111111111111111111111111111111111111111111111111111111111111111111111111111111111111111111111111111111111111111111111111111111111111111111111111111111111111111111111111111111111111111111111111111111111111111111111111111111111111111111111111111111111111111111111111111111111111111111111111111 [
b1100001011011000110110001011111011011110110111001100101 _
b11111111111111111111111111111111 \
b11111111111111111111111111111111111111111111111111111111111111111111111111111111111111111111111111111111111111111111111111111111111111111111111111111111111111111111111111111111111111111111111111111111111111111111111111111111111111111111111111111111111111111111111111111111111111111111111111111111111111111111111111111111111111111111111111111111111111111111111111111111111111111111111111111111111111111111111111111111111111111111111111111111111111111111111111111111111111111111111111111111111111111111111111111111111111111111111111111111111111111111111111111111111111111111111111111111111111111111111111111111111111111111111111111111111111111111111111111111111111111111111111111111111111111111111111111111111111111111111111111111111111111111111111111111111111111111111111111111111111111111111111111111111111111111111111111111111111111111111111111111111111111111111111111111111111111111111111111111111111111111111111111111111111111111111111111111111111111111111111111111111111111111111111111111111111111111111111111111111111111111111111111111111111111111111111111111111111111111111111111111111111111111111111111111111111111111111111111111111111111111111111111111111111111111111111111111111111111111111111111111111111111111111111111111111111111111111111111111111111111111111111111111111111111111111111111111111111111111111111111111111111111111111111111111111111111111111111111111111111111111111111111111111111111111111111111111111111111111111111111111111111111111111111111111111111111111111111111111111111111111111111111111111111111111111111111111111111111111111111111111111111111111111111111111111111111111111111111111111111111111111111111111111111111111111111111111111111111111111111111111111111111111111111111111111111111111111111111111111111111111111111111111111111111111111111111111111111111111111111111111111111111111111111111111111111111111111111111111111111111111111111111111111111111111111111111111111111111111111111111111111111111111111111111111111111111111111111111111111111111111111111111111111111111111111111111111111111111111111111111111 ]
04
0/
